Lab2/alu_func.v
// FuncCodes
`define FUNC_ADD    4'b0000
`define FUNC_SUB    4'b0001
`define FUNC_ID     4'b0010
`define FUNC_NOT    4'b0011
`define FUNC_AND    4'b0100
`define FUNC_OR     4'b0101
`define FUNC_NAND   4'b0110
`define FUNC_NOR    4'b0111
`define FUNC_XOR    4'b1000
`define FUNC_XNOR   4'b1001
`define FUNC_LLS    4'b1010
`define FUNC_LRS    4'b1011
`define FUNC_ALS    4'b1100
`define FUNC_ARS    4'b1101
`define FUNC_TCP    4'b1110
`define FUNC_ZERO   4'b1111

// Same from LAB1

Lab1/alu/alu.v
`include "alu_func.v"

module ALU #(parameter data_width = 16) (
	input [data_width - 1 : 0] A, 
	input [data_width - 1 : 0] B, 
	input [3 : 0] FuncCode,
    output reg [data_width - 1: 0] C,
    output reg OverflowFlag
);

initial begin
	C = 0;
	OverflowFlag = 0;
end   	

always @(*) begin
	OverflowFlag = 0;
	case(FuncCode)

		`FUNC_ADD : begin
			C = A + B;
			if ((A[data_width - 1] == B[data_width - 1]) && (C[data_width - 1] != A[data_width - 1]))
				OverflowFlag = 1;
		end
		`FUNC_SUB : begin
			C = A - B;
			if ((A[data_width - 1] != B[data_width - 1]) && (C[data_width - 1] != A[data_width - 1]))
				OverflowFlag = 1;
		end


		`FUNC_ID : C = A;		
		`FUNC_NOT : C = ~A;
		`FUNC_AND : C = A & B;
		`FUNC_OR : C = A | B;
		`FUNC_NAND : C = ~(A & B);
		`FUNC_NOR : C = ~(A | B);
		`FUNC_XOR : C = A ^ B;
		`FUNC_XNOR : C = ~(A ^ B);
		`FUNC_LLS : C = A << 1'b1;
		`FUNC_LRS : C = A >> 1'b1;
		`FUNC_ALS : C = A <<< 1'b1;
		`FUNC_ARS : C = A >>> 1'b1;
		`FUNC_TCP : C = ~A + 1'b1;
		`FUNC_ZERO : C = 0;
		default: C = 1'b0;
	endcase
end

endmodule

Lab1/alu/waveform.vcd
$version Generated by VerilatedVcd $end
$timescale 1ps $end
 $scope module TOP $end
  $var wire 16 # A [15:0] $end
  $var wire 16 $ B [15:0] $end
  $var wire 4 % FuncCode [3:0] $end
  $var wire 16 & C [15:0] $end
  $var wire 1 ' OverflowFlag $end
  $scope module ALU $end
   $var wire 32 ( data_width [31:0] $end
   $var wire 16 # A [15:0] $end
   $var wire 16 $ B [15:0] $end
   $var wire 4 % FuncCode [3:0] $end
   $var wire 16 & C [15:0] $end
   $var wire 1 ' OverflowFlag $end
  $upscope $end
 $upscope $end
$enddefinitions $end


#0
b0000000000000001 #
b0000000000000001 $
b0000 %
b0000000000000010 &
0'
b00000000000000000000000000010000 (
#1
#2
#3
#4
b0001 %
b0000000000000000 &
#5
#6
b0010 %
b0000000000000001 &
#7
#8
b0011 %
b1111111111111110 &
#9
#10
b0000000000001011 #
b0000000000000101 $
b0100 %
b0000000000000001 &
#11
#12
b0101 %
b0000000000001111 &
#13
#14
b0110 %
b1111111111111110 &
#15
#16
b0111 %
b1111111111110000 &
#17
#18
b1000 %
b0000000000001110 &
#19
#20
b1001 %
b1111111111110001 &
#21
#22
b1010 %
b0000000000010110 &
#23
#24
b1011 %
b0000000000000101 &
#25
#26
b1100 %
b0000000000010110 &
#27
#28
b1101 %
b0000000000000101 &
#29
#30
b1110 %
b1111111111110101 &
#31
#32
b1111 %
b0000000000000000 &
#33
#34
b0111111111111111 #
b0000000000000001 $
b0000 %
b1000000000000000 &
1'
#35
#36
b1000000000000000 #
b0001 %
b0111111111111111 &
